{
    "data":[
        {"name": "你好，李焕英", "url": "https://www.wanmeikk.me/play/3039_1_1.html", "parse": true},
	    {"name": "唐人街探案3", "url": "https://www.wanmeikk.me/play/3038_1_1.html", "parse": true},
	    {"name": "鬼灭之刃 剧场版 无限列车篇", "url": "https://www.wanmeikk.me/play/3037_1_1.html", "parse": true},
	    {"name": "晴雅集", "url": "https://www.wanmeikk.me/play/2906_1_1.html", "parse": true},
	    {"name": "人潮汹涌", "url": "https://www.wanmeikk.me/play/3036_1_1.html", "parse": true},
	    {"name": "哥斯拉大战金刚", "url": "https://www.wanmeikk.me/play/3033_1_1.html", "parse": true},
	    {"name": "扎克·施奈德版正义联盟", "url": "https://www.wanmeikk.me/play/3035_1_1.html", "parse": true},
	    {"name": "哆啦A梦：伴我同行2", "url": "https://www.wanmeikk.me/play/3034_1_1.html", "parse": true},
	    {"name": "刺杀小说家", "url": "https://www.wanmeikk.me/play/3032_1_1.html", "parse": true},
	    {"name": "打开心世界", "url": "https://www.wanmeikk.me/play/3031_1_1.html", "parse": true}
	    ]
}
